generic_exporters/__init__.py
generic_exporters/_awaitable.py
generic_exporters/_constant.py
generic_exporters/_mathable.py
generic_exporters/_time.py
generic_exporters/_types.py
generic_exporters/dataset.py
generic_exporters/metric.py
generic_exporters/plan.py
generic_exporters/py.typed
generic_exporters/timeseries.py
generic_exporters/processors/__init__.py
generic_exporters/processors/_base.py
generic_exporters/processors/framer.py
generic_exporters/processors/plotter.py
generic_exporters/processors/exporters/__init__.py
generic_exporters/processors/exporters/_base.py
generic_exporters/processors/exporters/exporter.py
generic_exporters/processors/exporters/datastores/__init__.py
generic_exporters/processors/exporters/datastores/default.py
generic_exporters/processors/exporters/datastores/timeseries/__init__.py
generic_exporters/processors/exporters/datastores/timeseries/_base.py
generic_exporters/processors/exporters/datastores/timeseries/multi.py
generic_exporters/processors/exporters/datastores/timeseries/sql.py
generic_exporters/processors/exporters/datastores/timeseries/victoria.py
generic_exporters-0.0.13.dist-info/METADATA
generic_exporters-0.0.13.dist-info/WHEEL
generic_exporters-0.0.13.dist-info/top_level.txt
generic_exporters-0.0.13.dist-info/RECORD
