Metadata-Version: 2.1
Name: generic-exporters
Version: 0.0.13
Summary: A lightweight library that provides generic data export helpers so I can deduplicate code across my various projects.
Home-page: https://github.com/BobTheBuidler/generic_exporters
Author: BobTheBuidler
Author-email: bobthebuidlerdefi@gmail.com
License: MIT
Requires-Dist: aiohttp
Requires-Dist: bqplot
Requires-Dist: ez-a-sync <0.34,>=0.33.3
Requires-Dist: inflection >=0.3.0
Requires-Dist: msgspec
Requires-Dist: pandas
Requires-Dist: pony
